src/__init__.py
src/cli.py
src/parser/__init__.py
src/parser/csv.py
src/parser/parser.py
src/parser/srt.py
src/parser/txt.py
src/translator/Helsinki.py
src/translator/__init__.py
src/translator/mt5ja2zh.py
src/translator/translator.py
local_first_linguist-0.2.1.dist-info/LICENSE
local_first_linguist-0.2.1.dist-info/METADATA
local_first_linguist-0.2.1.dist-info/WHEEL
local_first_linguist-0.2.1.dist-info/entry_points.txt
local_first_linguist-0.2.1.dist-info/top_level.txt
local_first_linguist-0.2.1.dist-info/RECORD
