Metadata-Version: 2.1
Name: local-first-linguist
Version: 0.2.1
Author-email: me@liangrunda.com
License: MIT
License-File: LICENSE
Requires-Dist: tqdm >=4.0.0
